{
  "schema_version": "0.1",
  "corpus_id": "skru-2",
  "description": "Контрольные вопросы-ответы по архиву СКРУ-2 (маркшейдерия, акты, стволы)",
  "tests": [
    {
      "id": "skru_001",
      "question": "акт проверки копра клетьевого ствола",
      "reference_answer": "Должен найтись акт проверки копра клетьевого ствола (маркшейдерия, КС).",
      "expect_any_in_citation": ["копр", "клетьев"],
      "expect_path_contains": "клетьев"
    },
    {
      "id": "skru_002",
      "question": "акт проверки подъемной машины скипового ствола",
      "reference_answer": "Документ об проверке подъемной машины скипового ствола (СС).",
      "expect_any_in_citation": ["скип", "подъем", "подъём"],
      "expect_path_contains": "скип"
    },
    {
      "id": "skru_003",
      "question": "акт заложения осей на подшкивной КС",
      "reference_answer": "Акт заложения осей на подшкивной (клетьевой ствол, КС).",
      "expect_any_in_citation": ["оси", "подшкив", "заложен"],
      "expect_path_contains": "подшкив"
    },
    {
      "id": "skru_004",
      "question": "акт передачи высотной отметки скиповой ствол",
      "reference_answer": "Акт передачи высотной отметки скипового ствола.",
      "expect_any_in_citation": ["высотн", "отметк", "скип"],
      "expect_path_contains": "скип"
    },
    {
      "id": "skru_005",
      "question": "вертикальность копра клетьевого ствола 2022",
      "reference_answer": "Схема/акт вертикальности копра клетьевого ствола за 2022 год.",
      "expect_any_in_citation": ["вертикальн", "копр", "2022"],
      "expect_path_contains": "2022"
    },
    {
      "id": "skru_006",
      "question": "акт ежегодной проверки копра ствола номер 1",
      "reference_answer": "Акт ежегодной проверки состояния копра ствола №1.",
      "expect_any_in_citation": ["ежегодн", "копр", "ствол"],
      "expect_path_contains": "№1"
    },
    {
      "id": "skru_007",
      "question": "углы девиации проходческой лебедки КС",
      "reference_answer": "Исполнительная схема углов девиации проходческой лебедки (КС).",
      "expect_any_in_citation": ["девиац", "лебедк", "проход"],
      "expect_path_contains": "лебедк"
    },
    {
      "id": "skru_008",
      "question": "акт разбивки в натуре образец",
      "reference_answer": "Акт о разбивке в натуре (образец маркшейдерского акта).",
      "expect_any_in_citation": ["разбивк", "натур"],
      "expect_path_contains": "разбивк"
    },
    {
      "id": "skru_009",
      "question": "оси ствола на подшкивной СС pdf",
      "reference_answer": "PDF с осями ствола на подшкивной (скиоповый ствол, СС).",
      "expect_any_in_citation": ["оси", "подшкив", "сс"],
      "expect_path_contains": "сс"
    },
    {
      "id": "skru_010",
      "question": "проверка двухбарабанной подъемной машины номер 2 клетьевого ствола",
      "reference_answer": "Акт проверки двухбарабанной подъемной машины №2 клетьевого ствола.",
      "expect_any_in_citation": ["двухбарабан", "подъем", "клетьев"],
      "expect_digits": ["2"]
    }
  ]
}
